src/__init__.py
src/commit_inquirer.py
src/config.py
src/des.py
src/git_handler.py
src/imit.py
src/jira_issues.py
src/option_handler.py
src/version_handler.py
imit-1.5.3.dist-info/LICENSE
imit-1.5.3.dist-info/METADATA
imit-1.5.3.dist-info/WHEEL
imit-1.5.3.dist-info/entry_points.txt
imit-1.5.3.dist-info/top_level.txt
imit-1.5.3.dist-info/RECORD
