Metadata-Version: 2.1
Name: imit
Version: 1.5.3
Summary: 提供交互或命令行的形式规范地提交git commit
Home-page: https://github.com/leytou
Author: leytou
Author-email: hi_litao@163.com
License: MIT
Keywords: python commit git
Classifier: Programming Language :: Python :: 3
Requires-Python: >=3.7
License-File: LICENSE
Requires-Dist: inquirer
Requires-Dist: docopt
Requires-Dist: GitPython
Requires-Dist: jira
Requires-Dist: pyDes
Requires-Dist: prompt-toolkit
